ml6_kfp_components/__init__.py
ml6_kfp_components/__pycache__/__init__.cpython-38.pyc
ml6_kfp_components/components/__init__.py
ml6_kfp_components/components/triton/__init__.py
ml6_kfp_components/components/triton/components.py
ml6_kfp_components/components/vertex/__init__.py
ml6_kfp_components/components/vertex/components.py
ml6_kfp_components/components/vertex/test_components.py
ml6_kfp_components/examples/__init__.py
ml6_kfp_components/examples/custom_image/Dockerfile
ml6_kfp_components/examples/custom_image/__init__.py
ml6_kfp_components/examples/custom_image/components.py
ml6_kfp_components/examples/custom_image/requirements.txt
ml6_kfp_components/examples/lightweight/__init__.py
ml6_kfp_components/examples/lightweight/components.py
ml6_kfp_components/examples/yaml_based/Dockerfile
ml6_kfp_components/examples/yaml_based/__init__.py
ml6_kfp_components/examples/yaml_based/components.py
ml6_kfp_components/examples/yaml_based/example_component.jinja.yaml
ml6_kfp_components/examples/yaml_based/requirements.txt
ml6_kfp_components/examples/yaml_based/src/__init__.py
ml6_kfp_components/examples/yaml_based/src/main.py
ml6_kfp_components/utils/__init__.py
ml6_kfp_components/utils/component_utils.py
ml6_kfp_components-0.0.1.dev8.dist-info/LICENSE
ml6_kfp_components-0.0.1.dev8.dist-info/METADATA
ml6_kfp_components-0.0.1.dev8.dist-info/WHEEL
ml6_kfp_components-0.0.1.dev8.dist-info/top_level.txt
ml6_kfp_components-0.0.1.dev8.dist-info/RECORD
