Metadata-Version: 2.1
Name: ml6-kfp-components
Version: 0.0.1.dev8
Summary: A compilation of ML6 shared KFP components.
Home-page: UNKNOWN
Author: Maximilian Gartz
Author-email: maximilian.gartz@ml6.eu
License: Apache License 2.0
Keywords: kfp,vertex-ai-pipelines,components
Platform: UNKNOWN
Requires-Python: >=3.7
Requires-Dist: kfp (==1.8.12)
Requires-Dist: Jinja2 (==3.0.3)
Requires-Dist: google-cloud-pipeline-components (==1.0.4)
Provides-Extra: all
Provides-Extra: dev
Requires-Dist: coverage[toml] (==6.3.2) ; extra == 'dev'
Requires-Dist: pytest (==7.1.1) ; extra == 'dev'
Requires-Dist: pytest-cov (==3.0.0) ; extra == 'dev'
Requires-Dist: flake8 (==3.8.3) ; extra == 'dev'
Requires-Dist: bandit[toml] (==1.7.4) ; extra == 'dev'
Requires-Dist: black (==22.3.0) ; extra == 'dev'
Requires-Dist: isort (==5.10.1) ; extra == 'dev'
Requires-Dist: mkdocs (==1.2.3) ; extra == 'dev'
Requires-Dist: mkdocs-material (==8.2.7) ; extra == 'dev'
Requires-Dist: mkdocstrings[python,python-legacy] (==0.18.1) ; extra == 'dev'
Requires-Dist: mkdocs-macros-plugin (==0.7.0) ; extra == 'dev'
Provides-Extra: docs
Requires-Dist: mkdocs (==1.2.3) ; extra == 'docs'
Requires-Dist: mkdocs-material (==8.2.7) ; extra == 'docs'
Requires-Dist: mkdocstrings[python,python-legacy] (==0.18.1) ; extra == 'docs'
Requires-Dist: mkdocs-macros-plugin (==0.7.0) ; extra == 'docs'
Provides-Extra: test
Requires-Dist: coverage[toml] (==6.3.2) ; extra == 'test'
Requires-Dist: pytest (==7.1.1) ; extra == 'test'
Requires-Dist: pytest-cov (==3.0.0) ; extra == 'test'
Requires-Dist: flake8 (==3.8.3) ; extra == 'test'
Requires-Dist: bandit[toml] (==1.7.4) ; extra == 'test'
Requires-Dist: black (==22.3.0) ; extra == 'test'
Requires-Dist: isort (==5.10.1) ; extra == 'test'
